CCIT/CCIT.py
CCIT/DataGen.py
CCIT/__init__.py
CCIT-0.3.dist-info/METADATA
CCIT-0.3.dist-info/WHEEL
CCIT-0.3.dist-info/top_level.txt
CCIT-0.3.dist-info/RECORD
